appmodern/__init__.py
appmodern/api.py
appmodern/app.py
appmodern/components.py
appmodern/create_page.py
appmodern/utils.py
appmodern-0.2.0.dist-info/licenses/LICENSE
appmodern-0.2.0.dist-info/METADATA
appmodern-0.2.0.dist-info/WHEEL
appmodern-0.2.0.dist-info/top_level.txt
appmodern-0.2.0.dist-info/RECORD
