Metadata-Version: 2.4
Name: appmodern
Version: 0.2.0
Summary: Uma biblioteca para criar aplicações visuais com Python e tecnologias web.
Home-page: https://github.com/GustavoSantiago1227
Author: Gustavo Felipe Felix Santiago
Author-email: gustavosantiago1227@gmail.com
Classifier: Programming Language :: Python :: 3
Classifier: License :: OSI Approved :: MIT License
Classifier: Operating System :: OS Independent
Classifier: Intended Audience :: Developers
Classifier: Topic :: Software Development :: Libraries :: Application Frameworks
Classifier: Topic :: Software Development :: User Interfaces
Requires-Python: >=3.6
License-File: LICENSE
Requires-Dist: pywebview
Dynamic: author
Dynamic: author-email
Dynamic: classifier
Dynamic: description
Dynamic: description-content-type
Dynamic: home-page
Dynamic: license-file
Dynamic: requires-dist
Dynamic: requires-python
Dynamic: summary
